LICENSE
MANIFEST.in
README.md
setup.py
django_redis_secure.egg-info/PKG-INFO
django_redis_secure.egg-info/SOURCES.txt
django_redis_secure.egg-info/dependency_links.txt
django_redis_secure.egg-info/requires.txt
django_redis_secure.egg-info/top_level.txt
secure_redis/__init__.py
secure_redis/secure_rq.py
secure_redis/serializer.py
secure_redis/settings.py
secure_redis/urls.py
secure_redis/views.py
secure_redis/tests/__init__.py
secure_redis/tests/test_secure_redis.py
secure_redis/tests/test_secure_rq.py